plico_dm_server/__init__.py
plico_dm_server/__version__.py
plico_dm_server/sandbox.py
plico_dm_server/calib/modal_basis/diag241.fits
plico_dm_server/calib/modulator/pi_calibration.py
plico_dm_server/calib/zonal_command/zero.fits
plico_dm_server/calib/zonal_command/zero_slm.fits
plico_dm_server/conf/plico_dm_server.conf
plico_dm_server/controller/__init__.py
plico_dm_server/controller/abstract_deformable_mirror.py
plico_dm_server/controller/abstract_modulator.py
plico_dm_server/controller/alpao_deformable_mirror.py
plico_dm_server/controller/bmc_deformable_mirror.py
plico_dm_server/controller/deformable_mirror_controller.py
plico_dm_server/controller/fake_alpao_dm.py
plico_dm_server/controller/fake_bmc_dm.py
plico_dm_server/controller/fake_meadowlark_slm_1920.py
plico_dm_server/controller/meadowlark_slm_1920.py
plico_dm_server/controller/pi_S334_modulator.py
plico_dm_server/controller/pi_tip_tilt_mirror.py
plico_dm_server/controller/plico_dm_run_controller.py
plico_dm_server/controller/runner.py
plico_dm_server/controller/simulated_deformable_mirror.py
plico_dm_server/controller/splatt_dm.py
plico_dm_server/process_monitor/__init__.py
plico_dm_server/process_monitor/plico_dm_run_process_monitor.py
plico_dm_server/scripts/__init__.py
plico_dm_server/scripts/plico_dm_controller.py
plico_dm_server/scripts/plico_dm_kill_processes.py
plico_dm_server/scripts/plico_dm_process_monitor.py
plico_dm_server/scripts/plico_dm_stop.py
plico_dm_server/utils/__init__.py
plico_dm_server/utils/constants.py
plico_dm_server/utils/process_startup_helper.py
plico_dm_server/utils/starter_script_creator.py
plico_dm_server-1.2.0.dist-info/LICENSE
plico_dm_server-1.2.0.dist-info/METADATA
plico_dm_server-1.2.0.dist-info/WHEEL
plico_dm_server-1.2.0.dist-info/entry_points.txt
plico_dm_server-1.2.0.dist-info/top_level.txt
plico_dm_server-1.2.0.dist-info/RECORD
