Metadata-Version: 2.1
Name: plico_dm_server
Version: 1.2.0
Summary: ALPAO, Boston MEMS, Physik Instrument Deformable mirrors interface
Home-page: https://github.com/ArcetriAdaptiveOptics/plico_dm_server
Author: Lorenzo Busoni
Author-email: lorenzo.busoni@inaf.it
License: MIT
Keywords: plico, deformable mirror, ALPAO, Boston MEMS, Physik Instrument, piezo, laboratory, instrumentation control
Classifier: Development Status :: 4 - Beta
Classifier: Operating System :: POSIX :: Linux
Classifier: Programming Language :: Python :: 3
License-File: LICENSE
Requires-Dist: plico >=0.30
Requires-Dist: plico-dm >=1.1.0
Requires-Dist: numpy
Requires-Dist: scipy
Requires-Dist: psutil
Requires-Dist: six
Requires-Dist: pi-gcs
Requires-Dist: pillow
